yatrie/__init__.py
yatrie/about.py
yatrie/trie.py
yatrie/utils.py
yatrie-0.1.0.dist-info/LICENSE
yatrie-0.1.0.dist-info/METADATA
yatrie-0.1.0.dist-info/WHEEL
yatrie-0.1.0.dist-info/top_level.txt
yatrie-0.1.0.dist-info/RECORD
